llama_index/multi_modal_llms/openvino/__init__.py
llama_index/multi_modal_llms/openvino/base.py
llama_index_multi_modal_llms_openvino-0.4.1.dist-info/METADATA
llama_index_multi_modal_llms_openvino-0.4.1.dist-info/WHEEL
llama_index_multi_modal_llms_openvino-0.4.1.dist-info/licenses/LICENSE
llama_index_multi_modal_llms_openvino-0.4.1.dist-info/RECORD
