Metadata-Version: 2.4
Name: llama-index-multi-modal-llms-openvino
Version: 0.4.1
Summary: llama-index multi_modal_llms openvino integration
Author-email: Your Name <you@example.com>
License-Expression: MIT
License-File: LICENSE
Requires-Python: <4.0,>=3.9
Requires-Dist: llama-index-core<0.15,>=0.13.0
Requires-Dist: llama-index-llms-openvino<1,>=0.5.0
Requires-Dist: optimum-intel[openvino]>=1.20.0
Requires-Dist: optimum[openvino]>=1.21.2
